[
   {
      "titre":"Maths",
      "texte":"Géométrie",
      "couleur":"blue",
      "cote":1,
      "ordre":1
   },
   {
      "titre":"Maths",
      "texte":"Algèbre",
      "couleur":"blue",
      "cote":1,
      "ordre":2
   },
   {
      "titre":"Chance",
      "texte":"",
      "couleur":"white",
      "cote":1,
      "ordre":3
   },
   {
      "titre":"Info",
      "texte":"Système",
      "couleur":"red",
      "cote":1,
      "ordre":4
   },
   {
      "titre":"Info",
      "texte":"Développement",
      "couleur":"red",
      "cote":1,
      "ordre":5
   },
   {
      "titre":"Français",
      "texte":"Rédaction",
      "couleur":"purple",
      "cote":2,
      "ordre":1
   },
   {
      "titre":"Français",
      "texte":"Littérature",
      "couleur":"purple",
      "cote":2,
      "ordre":2
   },
   {
      "titre":"Chance",
      "texte":"",
      "couleur":"white",
      "cote":2,
      "ordre":3
   },
   {
      "titre":"Méca",
      "texte":"Matériaux",
      "couleur":"green",
      "cote":2,
      "ordre":4
   },
   {
      "titre":"Méca",
      "texte":"Usinage",
      "couleur":"green",
      "cote":2,
      "ordre":5
   },
   {
      "titre":"Langues",
      "texte":"Allemand",
      "couleur":"yellow",
      "cote":3,
      "ordre":1
   },
   {
      "titre":"Langues",
      "texte":"Anglais",
      "couleur":"yellow",
      "cote":3,
      "ordre":2
   },
   {
      "titre":"Chance",
      "texte":"",
      "couleur":"white",
      "cote":3,
      "ordre":3
   },
   {
      "titre":"Média",
      "texte":"Multimédia",
      "couleur":"orange",
      "cote":3,
      "ordre":4
   },
   {
      "titre":"Média",
      "texte":"Web",
      "couleur":"orange",
      "cote":3,
      "ordre":5
   },
   {
      "titre":"ECG",
      "texte":"Economie",
      "couleur":"pink",
      "cote":4,
      "ordre":1
   },
   {
      "titre":"ECG",
      "texte":"Droit",
      "couleur":"pink",
      "cote":4,
      "ordre":2
   },
   {
      "titre":"Chance",
      "texte":"",
      "couleur":"white",
      "cote":4,
      "ordre":3
   },
   {
      "titre":"Sport",
      "texte":"Foot",
      "couleur":"cyan",
      "cote":4,
      "ordre":4
   },
   {
      "titre":"Sport",
      "texte":"Basket",
      "couleur":"cyan",
      "cote":4,
      "ordre":5
   }
]
